Adafruit_ADS1x15-1.0.2.dist-info/metadata.json
Adafruit_ADS1x15-1.0.2.dist-info/METADATA
Adafruit_ADS1x15-1.0.2.dist-info/RECORD
Adafruit_ADS1x15-1.0.2.dist-info/WHEEL
Adafruit_ADS1x15-1.0.2.dist-info/DESCRIPTION.rst
Adafruit_ADS1x15-1.0.2.dist-info/dependency_links.txt
Adafruit_ADS1x15-1.0.2.dist-info/top_level.txt
Adafruit_ADS1x15/ADS1x15.py
Adafruit_ADS1x15/__init__.py
